episodescript.py
episodescript-0.1.1.dist-info/LICENSE
episodescript-0.1.1.dist-info/METADATA
episodescript-0.1.1.dist-info/WHEEL
episodescript-0.1.1.dist-info/entry_points.txt
episodescript-0.1.1.dist-info/top_level.txt
episodescript-0.1.1.dist-info/RECORD
