Metadata-Version: 2.1
Name: episodescript
Version: 0.1.1
Summary: Scraper for TV show episode script
Home-page: https://github.com/kota7/episodescript
Author: Kota Mori
Author-email: kmori05@gmail.com
License: UNKNOWN
Platform: UNKNOWN
Classifier: Development Status :: 3 - Alpha
Classifier: License :: OSI Approved :: MIT License
Classifier: Programming Language :: Python :: 2.7
Classifier: Programming Language :: Python :: 3.4
Classifier: Programming Language :: Python :: 3.5
Classifier: Programming Language :: Python :: 3.6
Classifier: Programming Language :: Python :: 3.7
Requires-Dist: beautifulsoup4
Requires-Dist: html5lib (<1)
